femedu/__init__.py
femedu/domain/Beam2dTransformation.py
femedu/domain/BeamTransformation.py
femedu/domain/CosseratTransformation.py
femedu/domain/Frame2dTransformation.py
femedu/domain/FrameTransformation.py
femedu/domain/Node.py
femedu/domain/Solid2dTransformation.py
femedu/domain/SolidTransformation.py
femedu/domain/System.py
femedu/domain/Transformation.py
femedu/domain/__init__.py
femedu/elements/DrawElement.py
femedu/elements/Element.py
femedu/elements/Face2D.py
femedu/elements/Face3D.py
femedu/elements/Faces.py
femedu/elements/LinearElement.py
femedu/elements/__init__.py
femedu/elements/diffusion/Triangle.py
femedu/elements/diffusion/Triangle6.py
femedu/elements/diffusion/__init__.py
femedu/elements/direct/Beam2D.py
femedu/elements/direct/Frame2D.py
femedu/elements/direct/Truss.py
femedu/elements/direct/__init__.py
femedu/elements/finite/Frame2D.py
femedu/elements/finite/Quad.py
femedu/elements/finite/Quad8.py
femedu/elements/finite/Quad9.py
femedu/elements/finite/Triangle.py
femedu/elements/finite/Triangle6.py
femedu/elements/finite/Truss.py
femedu/elements/finite/__init__.py
femedu/elements/linear/Beam2D.py
femedu/elements/linear/BeamSolidLink.py
femedu/elements/linear/Frame2D.py
femedu/elements/linear/HRQuad.py
femedu/elements/linear/Quad.py
femedu/elements/linear/Quad8.py
femedu/elements/linear/Quad9.py
femedu/elements/linear/ReducedIntegrationQuad.py
femedu/elements/linear/Spring.py
femedu/elements/linear/Triangle.py
femedu/elements/linear/Triangle6.py
femedu/elements/linear/Truss.py
femedu/elements/linear/__init__.py
femedu/examples/Example.py
femedu/examples/README.rst
femedu/examples/__init__.py
femedu/examples/runall.py
femedu/examples/beams/__init__.py
femedu/examples/beams/beam01.py
femedu/examples/beams/beam02.py
femedu/examples/beams/runall.py
femedu/examples/frames/__init__.py
femedu/examples/frames/frame01.py
femedu/examples/frames/frame02.py
femedu/examples/frames/frame03.py
femedu/examples/frames/frame04.py
femedu/examples/frames/runall.py
femedu-1.0.30.dist-info/licenses/LICENSE
femedu-1.0.30.dist-info/WHEEL
femedu-1.0.30.dist-info/METADATA
femedu-1.0.30.dist-info/RECORD
