Metadata-Version: 2.4
Name: femedu
Version: 1.0.30
Summary: FEM.edu is nonlinear finite element code designed for use in higher education
Author-email: Peter Mackenzie-Helnwein <pmackenz@uw.edu>, Tatsuhiko Sweet <sweetta@uw.edu>, William Galik <william.galik@iusspavia.it>, Jordan Seawright <jseawrig@uw.edu>
Requires-Python: >=3.10
Classifier: License :: OSI Approved :: GNU General Public License v3 or later (GPLv3+)
License-File: LICENSE
Requires-Dist: numpy >=1.23
Requires-Dist: scipy >=1.10.1
Requires-Dist: matplotlib >=3.5
Requires-Dist: pandas
Project-URL: Documentation, https://pmackenz.github.io/FEM.edu.documentation/
